qiniustorage/__init__.py
qiniustorage/backends.py
qiniustorage/utils.py
django_qiniu_storage_full-2.3.101.dist-info/LICENSE
django_qiniu_storage_full-2.3.101.dist-info/METADATA
django_qiniu_storage_full-2.3.101.dist-info/WHEEL
django_qiniu_storage_full-2.3.101.dist-info/top_level.txt
django_qiniu_storage_full-2.3.101.dist-info/RECORD
